{
    "openapi": "3.0.0",
    "info": {
        "title": "RTGK API",
        "description": "RTGK API documentation",
        "contact": {
            "email": "pavlo.malovanyi@kyivcity.gov.ua"
        },
        "license": {
            "name": "Apache 2.0",
            "url": "https://www.apache.org/licenses/LICENSE-2.0.html"
        },
        "version": "1.0.0"
    },
    "paths": {
        "/api/notifications": {
            "get": {
                "tags": [
                    "notifications"
                ],
                "operationId": "911565ad9aff9ba7eded3f189509e578",
                "responses": {
                    "200": {
                        "description": "Returns some sample category things",
                        "content": {
                            "application/json": {
                                "schema": {}
                            }
                        }
                    },
                    "400": {
                        "description": "Error: Bad request. When required parameters were not supplied."
                    }
                }
            }
        }
    }
}